graphanno/__init__.py
graphanno/graphanno.py
tests/test_objects/__init__.py
tests/test_objects/advanced.py
tests/test_objects/basic.py
tests/test_objects/duplicated.py
tests/test_objects/full_example.py
tests/test_objects/nested.py
graphanno-1.3.1.dist-info/LICENSE
graphanno-1.3.1.dist-info/METADATA
graphanno-1.3.1.dist-info/WHEEL
graphanno-1.3.1.dist-info/top_level.txt
graphanno-1.3.1.dist-info/RECORD
