Metadata-Version: 2.1
Name: graphanno
Version: 1.3.1
Summary: Create graphene ObjectType based on the type annotations.
Home-page: https://github.com/aklajnert/graphanno
Author: Andrzej Klajnert
Author-email: py@aklajnert.pl
License: MIT
Project-URL: Bug Reports, https://github.com/aklajnert/graphanno/issues
Project-URL: Source, https://github.com/aklajnert/graphanno
Keywords: graphene graphql type_annotations annotations
Platform: UNKNOWN
Classifier: Development Status :: 4 - Beta
Classifier: Intended Audience :: Developers
Classifier: Topic :: Software Development :: Code Generators
Classifier: License :: OSI Approved :: MIT License
Classifier: Programming Language :: Python :: 3 :: Only
Classifier: Programming Language :: Python :: 3.6
Classifier: Programming Language :: Python :: 3.7
Classifier: Programming Language :: Python :: 3.8
Requires-Python: >=3.6, <4
Requires-Dist: graphene (<3,>=2.0)
Provides-Extra: test
Requires-Dist: pytest ; extra == 'test'
Requires-Dist: pylint ; extra == 'test'
Requires-Dist: flake8 ; extra == 'test'
